divide5_mihai.v
// good module with 50% duty cycle
module divide5_mihai(
    input reset,
    input clk,
    output out
);

	reg mid_1, mid_2, mid_3;

	always @(posedge clk) begin
		if (~reset) begin
        	mid_1 <= 0;
        	mid_2 <= 0;
			mid_3 <= 0;
    	end else begin
			mid_1 <= ~mid_2 & mid_3;
			mid_2 <= ~mid_1 & ~mid_3;
			mid_3 <= mid_2;
		end
	end
	assign out = (clk & mid_3) | mid_2;	
	
endmodule

divide3_mihai.v
// good module with 50% duty cycle
module divide3_mihai(
    input reset,
    input clk,
    output out
);

	reg mid_1;
	reg mid_2;

	always @(posedge clk) begin
		if (~reset) begin
        	mid_1 <= 0;
        	mid_2 <= 0;
    	end else begin
			mid_1 <= ~mid_1 & ~mid_2;
			mid_2 <= ~mid_2 | mid_1;
		end
	end
	assign out = (clk & mid_2) | mid_1;	
	
endmodule

divideby2.v
module divideby2 (
  input      rst_n,
  input      clk_rx,
  output reg clk_tx
);

always @ (posedge clk_rx) begin
  if (~rst_n) begin
    clk_tx <= 1'b0;
  end
  else begin
    clk_tx <= ~clk_tx;
  end
end

endmodule

	// integer count = 0;
	// always @(posedge clk or negedge clk) begin
	// 	if (count == 3)
	// 		q <= 1;
	// 	else if (count == 6) begin
	//     	q <= 0;
	//     	count = 0;
	// 	end
	// 	else if (count == 0)
	// 		q <= 0;
	// 	count = count + 1;
	// end

CLKDIVS.v
module CLKDIVS(
	input reset,
    input clk,
    output div2,
	output div3,
	output div5
);

	divideby2 divide2(
		.rst_n(reset),
		.clk_rx(clk),
		.clk_tx(div2)
    );

	divide3_mihai divide3(
		.reset(reset),
		.clk(clk),
		.out(div3)
	);

	divide5_mihai divide5(
		.reset(reset),
		.clk(clk),
		.out(div5)
	);

endmodule

testbench.v
module testbench();
	reg clk;
	output wire q;
	output reg rst;
	output wire q1;
	output wire q2;
	
// initial
// clk = 1'b0;
	
	// divide_by_3 dut(
	// 	.clk(clk),
	// 	.q(q)
	// );
	// divideby2 dut_2 (rst,clk, q);
	// divide_by_3 dut_3 (clk, q1);
	// divideby3 dut_3_2 (clk, q2);
	// divide_by_3_chtgpt dut_3_3 (rst,clk, q);
	CLKDIVS dut (rst,clk, q, q1, q2);
	// divide5_mihai dut2 (rst,clk, q1);
	initial begin
		rst = 0;
	  clk = 1;
	  forever #1 clk = ~clk;
	end
	
	initial begin
		$dumpvars;
		$monitor("Time: %0d ns, clk: %b, q: %b q1: %b", $time, clk, q, q1);
		rst =0;
		#2 rst =1;
	  #100 $finish;
	end
endmodule

divideby3.v
// good module with 50% duty cycle hack (dosnt synthisize)
module divideby3 (
	input clk,
	output reg q
);
	reg [2:0] count = 0;
	always @(posedge clk or negedge clk) begin
		if (count == 3)
			q = 1;
		else if (count == 6) begin
	    	q = ~q;
	    	count = 0;
		end
		else if (count == 0)
			q = 0;
		count <= count + 1;
	end
endmodule

divide5.v
module divide5(
    input reset,
    input clk,
    output reg out
);

	reg [3:0] count;

always @(posedge clk or posedge reset) begin
	if (~reset) begin
        count <= 0;
        out <= 0;
    end else begin
        count <= count + 1;
		if (count == 3)
			out <= 1;
		else if (count == 4) begin
            count <= 0;
        end 
		else if (count == 0)begin
        		out <= 0;
		end
    end
end

endmodule

divide3_trial.v
// good module without 50% duty cycle
module divide3_trail(
    input reset,
    input clk,
    output out
);

	reg [1:0] count;
	assign out = count[1] & ~count[0];

always @(posedge clk or posedge reset) begin
	if (~reset) begin
        count <= 0;
    end else begin
        count <= count + 1;
		if (count == 2) begin
            count <= 0;
        end 
    end
end

endmodule

divide3.v
module divide3(
    input reset,
    input clk,
    output reg out
);

	reg [1:0] count;

always @(posedge clk or posedge reset) begin
	if (~reset) begin
        count <= 0;
        out <= 0;
    end else begin
        count <= count + 1;
		if (count == 2) begin
            count <= 0;
			out <= 1;
        end 
		else if (count == 0)begin
        		out <= 0;
		end
    end
end

endmodule

adder.v
module adder (
    input a,
    input b,
    output s,
    output c
);
    // assign {c, s} = a + b;
	assign s = a ^ b;
	assign c = a & b;
endmodule

build/dump.vcd
$date
	Wed Mar  8 15:04:45 2023
$end
$version
	Icarus Verilog
$end
$timescale
	1s
$end
$scope module adder $end
$var wire 1 ! a $end
$var wire 1 " b $end
$var wire 1 # c $end
$var wire 1 $ s $end
$upscope $end
$scope module divide3 $end
$var wire 1 % clk $end
$var wire 1 & reset $end
$var reg 2 ' count [1:0] $end
$var reg 1 ( out $end
$upscope $end
$scope module divide3_trail $end
$var wire 1 ) clk $end
$var wire 1 * out $end
$var wire 1 + reset $end
$var reg 2 , count [1:0] $end
$upscope $end
$scope module divide5 $end
$var wire 1 - clk $end
$var wire 1 . reset $end
$var reg 4 / count [3:0] $end
$var reg 1 0 out $end
$upscope $end
$scope module divideby3 $end
$var wire 1 1 clk $end
$var reg 3 2 count [2:0] $end
$var reg 1 3 q $end
$upscope $end
$scope module testbench $end
$var wire 1 4 q2 $end
$var wire 1 5 q1 $end
$var wire 1 6 q $end
$var reg 1 7 clk $end
$var reg 1 8 rst $end
$scope module dut $end
$var wire 1 7 clk $end
$var wire 1 8 reset $end
$var wire 1 4 div5 $end
$var wire 1 5 div3 $end
$var wire 1 6 div2 $end
$scope module divide2 $end
$var wire 1 7 clk_rx $end
$var wire 1 8 rst_n $end
$var reg 1 6 clk_tx $end
$upscope $end
$scope module divide3 $end
$var wire 1 7 clk $end
$var wire 1 5 out $end
$var wire 1 8 reset $end
$var reg 1 9 mid_1 $end
$var reg 1 : mid_2 $end
$upscope $end
$scope module divide5 $end
$var wire 1 7 clk $end
$var wire 1 4 out $end
$var wire 1 8 reset $end
$var reg 1 ; mid_1 $end
$var reg 1 < mid_2 $end
$var reg 1 = mid_3 $end
$upscope $end
$upscope $end
$upscope $end
$enddefinitions $end
#0
$dumpvars
0=
0<
0;
0:
09
08
17
06
05
04
x3
b0 2
z1
x0
bx /
z.
z-
bx ,
z+
x*
z)
x(
bx '
z&
z%
x$
x#
z"
z!
$end
#1
07
#2
14
15
1<
1:
19
16
17
18
#3
07
#4
06
09
1=
17
#5
05
07
#6
0<
0:
16
05
17
#7
04
07
#8
15
06
1:
19
0=
1;
04
17
#9
07
#10
0;
09
16
17
#11
05
07
#12
14
06
0:
1<
05
17
#13
07
#14
15
1=
1:
19
16
17
#15
07
#16
06
09
0<
17
#17
05
04
07
#18
0=
1;
0:
16
05
04
17
#19
07
#20
15
06
1:
19
0;
17
#21
07
#22
14
1<
09
16
17
#23
05
07
#24
06
0:
1=
05
17
#25
07
#26
15
0<
1:
19
16
17
#27
04
07
#28
06
09
0=
1;
04
17
#29
05
07
#30
0;
0:
16
05
17
#31
07
#32
15
14
06
1:
19
1<
17
#33
07
#34
1=
09
16
17
#35
05
07
#36
06
0:
0<
05
17
#37
04
07
#38
15
0=
1;
1:
19
16
04
17
#39
07
#40
06
09
0;
17
#41
05
07
#42
14
1<
0:
16
05
17
#43
07
#44
15
06
1:
19
1=
17
#45
07
#46
0<
09
16
17
#47
05
04
07
#48
06
0:
0=
1;
05
04
17
#49
07
#50
15
0;
1:
19
16
17
#51
07
#52
14
06
09
1<
17
#53
05
07
#54
1=
0:
16
05
17
#55
07
#56
15
06
1:
19
0<
17
#57
04
07
#58
0=
1;
09
16
04
17
#59
05
07
#60
06
0:
0;
05
17
#61
07
#62
14
15
1<
1:
19
16
17
#63
07
#64
06
09
1=
17
#65
05
07
#66
0<
0:
16
05
17
#67
04
07
#68
15
06
1:
19
0=
1;
04
17
#69
07
#70
0;
09
16
17
#71
05
07
#72
14
06
0:
1<
05
17
#73
07
#74
15
1=
1:
19
16
17
#75
07
#76
06
09
0<
17
#77
05
04
07
#78
0=
1;
0:
16
05
04
17
#79
07
#80
15
06
1:
19
0;
17
#81
07
#82
14
1<
09
16
17
#83
05
07
#84
06
0:
1=
05
17
#85
07
#86
15
0<
1:
19
16
17
#87
04
07
#88
06
09
0=
1;
04
17
#89
05
07
#90
0;
0:
16
05
17
#91
07
#92
15
14
06
1:
19
1<
17
#93
07
#94
1=
09
16
17
#95
05
07
#96
06
0:
0<
05
17
#97
04
07
#98
15
0=
1;
1:
19
16
04
17
#99
07
#100
06
09
0;
17
#101
05
07
#102
14
1<
0:
16
05
17
