divide5.v
module divide5(
    input reset,
    input clk,
    output reg out
);

	reg [3:0] count;

always @(posedge clk or posedge reset) begin
	if (~reset) begin
        count <= 0;
        out <= 0;
    end else begin
        count <= count + 1;
		if (count == 3)
			out <= 1;
		else if (count == 4) begin
            count <= 0;
        end 
		else if (count == 0)begin
        		out <= 0;
		end
    end
end

endmodule

divide3.v
module divide3(
    input reset,
    input clk,
    output reg out
);

	reg [1:0] count;

always @(posedge clk or posedge reset) begin
	if (~reset) begin
        count <= 0;
        out <= 0;
    end else begin
        count <= count + 1;
		if (count == 2) begin
            count <= 0;
			out <= 1;
        end 
		else if (count == 0)begin
        		out <= 0;
		end
    end
end

endmodule

testbench.v
module testbench();
	reg clk;
	output wire q;
	output reg rst;
	output wire q1;
	// output wire q2;
	
// initial
// clk = 1'b0;
	
	// divide_by_3 dut(
	// 	.clk(clk),
	// 	.q(q)
	// );
	// divideby2 dut_2 (rst,clk, q);
	// divide_by_3 dut_3 (clk, q1);
	// divideby3 dut_3_2 (clk, q2);
	// divide_by_3_chtgpt dut_3_3 (rst,clk, q);
	divide3 dut (rst,clk, q);
	divide5 dut2 (rst,clk, q1);
	initial begin
		rst = 0;
	  clk = 1;
	  forever #1 clk = ~clk;
	end
	
	initial begin
		$dumpvars;
		$monitor("Time: %0d ns, clk: %b, q: %b q1: %b", $time, clk, q, q1);
		rst =0;
		#2 rst =1;
	  #100 $finish;
	end
endmodule

divideby3.v
// good module with 50% duty cycle hack (dosnt synthisize)
module divideby3 (
	input clk,
	output reg q
);
	reg [2:0] count = 0;
	always @(posedge clk or negedge clk) begin
		if (count == 3)
			q = 1;
		else if (count == 6) begin
	    	q = ~q;
	    	count = 0;
		end
		else if (count == 0)
			q = 0;
		count <= count + 1;
	end
endmodule

divideby2.v
module divideby2 (
  input      rst_n,
  input      clk_rx,
  output reg clk_tx
);

always @ (posedge clk_rx) begin
  if (~rst_n) begin
    clk_tx <= 1'b0;
  end
  else begin
    clk_tx <= ~clk_tx;
  end
end

endmodule

	// integer count = 0;
	// always @(posedge clk or negedge clk) begin
	// 	if (count == 3)
	// 		q <= 1;
	// 	else if (count == 6) begin
	//     	q <= 0;
	//     	count = 0;
	// 	end
	// 	else if (count == 0)
	// 		q <= 0;
	// 	count = count + 1;
	// end

divide_by_3_chtgpt.v
module divide_by_3_chtgpt (
	input		rst_n,
	input		clk_in,
	output reg	clk_out
);

reg [1:0] count;

always @(posedge clk_in) begin
	if (~rst_n) begin
		count <= 0;
		clk_out <= 0;
	end
	else begin
		count <= count + 1;
		if (count == 2) begin
			count <= 0;
			clk_out <= ~clk_out;
		end
	end
end

endmodule

divide_by_3.v
module divide_by_3 (
	input clk,
	output reg q
);
	reg [2:0] count = 0;
	always @(posedge clk) begin
		if (count == 2)
			q = 1;
			// count =  count + 1 
		else if (count == 3) begin
	    	q = 0;
	    	count = 0;
	  	end
		else if (count == 0)
			q = 0;
		count = count + 1;
	end
endmodule

adder.v
module adder (
    input a,
    input b,
    output s,
    output c
);
    // assign {c, s} = a + b;
	assign s = a ^ b;
	assign c = a & b;
endmodule

build/dump.vcd
$date
	Mon Mar  6 07:16:02 2023
$end
$version
	Icarus Verilog
$end
$timescale
	1s
$end
$scope module adder $end
$var wire 1 ! a $end
$var wire 1 " b $end
$var wire 1 # c $end
$var wire 1 $ s $end
$upscope $end
$scope module divide_by_3 $end
$var wire 1 % clk $end
$var reg 3 & count [2:0] $end
$var reg 1 ' q $end
$upscope $end
$scope module divide_by_3_chtgpt $end
$var wire 1 ( clk_in $end
$var wire 1 ) rst_n $end
$var reg 1 * clk_out $end
$var reg 2 + count [1:0] $end
$upscope $end
$scope module divideby2 $end
$var wire 1 , clk_rx $end
$var wire 1 - rst_n $end
$var reg 1 . clk_tx $end
$upscope $end
$scope module divideby3 $end
$var wire 1 / clk $end
$var reg 3 0 count [2:0] $end
$var reg 1 1 q $end
$upscope $end
$scope module testbench $end
$var wire 1 2 q1 $end
$var wire 1 3 q $end
$var reg 1 4 clk $end
$var reg 1 5 rst $end
$scope module dut $end
$var wire 1 4 clk $end
$var wire 1 5 reset $end
$var reg 2 6 count [1:0] $end
$var reg 1 3 out $end
$upscope $end
$scope module dut2 $end
$var wire 1 4 clk $end
$var wire 1 5 reset $end
$var reg 4 7 count [3:0] $end
$var reg 1 2 out $end
$upscope $end
$upscope $end
$enddefinitions $end
#0
$dumpvars
b0 7
b0 6
05
14
03
02
x1
b0 0
z/
x.
z-
z,
bx +
x*
z)
z(
x'
b0 &
z%
x$
x#
z"
z!
$end
#1
04
#2
b1 7
b1 6
14
15
#3
04
#4
b10 6
b10 7
14
#5
04
#6
b11 7
13
b0 6
14
#7
04
#8
03
b1 6
12
b100 7
14
#9
04
#10
b0 7
b10 6
14
#11
04
#12
13
b0 6
02
b1 7
14
#13
04
#14
b10 7
03
b1 6
14
#15
04
#16
b10 6
b11 7
14
#17
04
#18
12
b100 7
13
b0 6
14
#19
04
#20
03
b1 6
b0 7
14
#21
04
#22
02
b1 7
b10 6
14
#23
04
#24
13
b0 6
b10 7
14
#25
04
#26
b11 7
03
b1 6
14
#27
04
#28
b10 6
12
b100 7
14
#29
04
#30
b0 7
13
b0 6
14
#31
04
#32
03
b1 6
02
b1 7
14
#33
04
#34
b10 7
b10 6
14
#35
04
#36
13
b0 6
b11 7
14
#37
04
#38
12
b100 7
03
b1 6
14
#39
04
#40
b10 6
b0 7
14
#41
04
#42
02
b1 7
13
b0 6
14
#43
04
#44
03
b1 6
b10 7
14
#45
04
#46
b11 7
b10 6
14
#47
04
#48
13
b0 6
12
b100 7
14
#49
04
#50
b0 7
03
b1 6
14
#51
04
#52
b10 6
02
b1 7
14
#53
04
#54
b10 7
13
b0 6
14
#55
04
#56
03
b1 6
b11 7
14
#57
04
#58
12
b100 7
b10 6
14
#59
04
#60
13
b0 6
b0 7
14
#61
04
#62
02
b1 7
03
b1 6
14
#63
04
#64
b10 6
b10 7
14
#65
04
#66
b11 7
13
b0 6
14
#67
04
#68
03
b1 6
12
b100 7
14
#69
04
#70
b0 7
b10 6
14
#71
04
#72
13
b0 6
02
b1 7
14
#73
04
#74
b10 7
03
b1 6
14
#75
04
#76
b10 6
b11 7
14
#77
04
#78
12
b100 7
13
b0 6
14
#79
04
#80
03
b1 6
b0 7
14
#81
04
#82
02
b1 7
b10 6
14
#83
04
#84
13
b0 6
b10 7
14
#85
04
#86
b11 7
03
b1 6
14
#87
04
#88
b10 6
12
b100 7
14
#89
04
#90
b0 7
13
b0 6
14
#91
04
#92
03
b1 6
02
b1 7
14
#93
04
#94
b10 7
b10 6
14
#95
04
#96
13
b0 6
b11 7
14
#97
04
#98
12
b100 7
03
b1 6
14
#99
04
#100
b10 6
b0 7
14
#101
04
#102
02
b1 7
13
b0 6
14
