bing_divider.v
module bing_divider(
    input reset,
    input clk,
    output reg out
);

	reg [1:0] count;

always @(posedge clk or posedge reset) begin
	if (~reset) begin
        count <= 0;
        out <= 0;
    end else begin
        count <= count + 1;
		if (count == 2) begin
            count <= 0;
			out <= 1;
        end 
		else if (count == 0)begin
        		out <= 0;
		end
    end
end

endmodule

testbench.v
module testbench();
	reg clk;
	output wire q;
	output reg rst;
	// output wire q1;
	// output wire q2;
	
// initial
// clk = 1'b0;
	
	// divide_by_3 dut(
	// 	.clk(clk),
	// 	.q(q)
	// );
	// divideby2 dut_2 (rst,clk, q);
	// divide_by_3 dut_3 (clk, q1);
	// divideby3 dut_3_2 (clk, q2);
	// divide_by_3_chtgpt dut_3_3 (rst,clk, q);
	bing_divider dut (rst,clk, q);

	initial begin
		rst = 0;
	  clk = 1;
	  forever #1 clk = ~clk;
	end
	
	initial begin
		$dumpvars;
		$monitor("Time: %0d ns, clk: %b, q: %b", $time, clk, q);
		rst =0;
		#2 rst =1;
	  #100 $finish;
	end
endmodule

divideby3.v
// good module with 50% duty cycle hack (dosnt synthisize)
module divideby3 (
	input clk,
	output reg q
);
	reg [2:0] count = 0;
	always @(posedge clk or negedge clk) begin
		if (count == 3)
			q = 1;
		else if (count == 6) begin
	    	q = ~q;
	    	count = 0;
		end
		else if (count == 0)
			q = 0;
		count <= count + 1;
	end
endmodule

divideby2.v
module divideby2 (
  input      rst_n,
  input      clk_rx,
  output reg clk_tx
);

always @ (posedge clk_rx) begin
  if (~rst_n) begin
    clk_tx <= 1'b0;
  end
  else begin
    clk_tx <= ~clk_tx;
  end
end

endmodule

	// integer count = 0;
	// always @(posedge clk or negedge clk) begin
	// 	if (count == 3)
	// 		q <= 1;
	// 	else if (count == 6) begin
	//     	q <= 0;
	//     	count = 0;
	// 	end
	// 	else if (count == 0)
	// 		q <= 0;
	// 	count = count + 1;
	// end

divide_by_3_chtgpt.v
module divide_by_3_chtgpt (
	input		rst_n,
	input		clk_in,
	output reg	clk_out
);

reg [1:0] count;

always @(posedge clk_in) begin
	if (~rst_n) begin
		count <= 0;
		clk_out <= 0;
	end
	else begin
		count <= count + 1;
		if (count == 2) begin
			count <= 0;
			clk_out <= ~clk_out;
		end
	end
end

endmodule

divide_by_3.v
module divide_by_3 (
	input clk,
	output reg q
);
	reg [2:0] count = 0;
	always @(posedge clk) begin
		if (count == 2)
			q = 1;
			// count =  count + 1 
		else if (count == 3) begin
	    	q = 0;
	    	count = 0;
	  	end
		else if (count == 0)
			q = 0;
		count = count + 1;
	end
endmodule

adder.v
module adder (
    input a,
    input b,
    output s,
    output c
);
    // assign {c, s} = a + b;
	assign s = a ^ b;
	assign c = a & b;
endmodule

build/dump.vcd
$date
	Wed Mar  1 16:50:07 2023
$end
$version
	Icarus Verilog
$end
$timescale
	1s
$end
$scope module adder $end
$var wire 1 ! a $end
$var wire 1 " b $end
$var wire 1 # c $end
$var wire 1 $ s $end
$upscope $end
$scope module divide_by_3 $end
$var wire 1 % clk $end
$var reg 3 & count [2:0] $end
$var reg 1 ' q $end
$upscope $end
$scope module divide_by_3_chtgpt $end
$var wire 1 ( clk_in $end
$var wire 1 ) rst_n $end
$var reg 1 * clk_out $end
$var reg 2 + count [1:0] $end
$upscope $end
$scope module divideby2 $end
$var wire 1 , clk_rx $end
$var wire 1 - rst_n $end
$var reg 1 . clk_tx $end
$upscope $end
$scope module divideby3 $end
$var wire 1 / clk $end
$var reg 3 0 count [2:0] $end
$var reg 1 1 q $end
$upscope $end
$scope module testbench $end
$var wire 1 2 q $end
$var reg 1 3 clk $end
$var reg 1 4 rst $end
$scope module dut $end
$var wire 1 3 clk $end
$var wire 1 4 reset $end
$var reg 2 5 count [1:0] $end
$var reg 1 2 out $end
$upscope $end
$upscope $end
$enddefinitions $end
#0
$dumpvars
b0 5
04
13
02
x1
b0 0
z/
x.
z-
z,
bx +
x*
z)
z(
x'
b0 &
z%
x$
x#
z"
z!
$end
#1
03
#2
b1 5
13
14
#3
03
#4
b10 5
13
#5
03
#6
12
b0 5
13
#7
03
#8
02
b1 5
13
#9
03
#10
b10 5
13
#11
03
#12
12
b0 5
13
#13
03
#14
02
b1 5
13
#15
03
#16
b10 5
13
#17
03
#18
12
b0 5
13
#19
03
#20
02
b1 5
13
#21
03
#22
b10 5
13
#23
03
#24
12
b0 5
13
#25
03
#26
02
b1 5
13
#27
03
#28
b10 5
13
#29
03
#30
12
b0 5
13
#31
03
#32
02
b1 5
13
#33
03
#34
b10 5
13
#35
03
#36
12
b0 5
13
#37
03
#38
02
b1 5
13
#39
03
#40
b10 5
13
#41
03
#42
12
b0 5
13
#43
03
#44
02
b1 5
13
#45
03
#46
b10 5
13
#47
03
#48
12
b0 5
13
#49
03
#50
02
b1 5
13
#51
03
#52
b10 5
13
#53
03
#54
12
b0 5
13
#55
03
#56
02
b1 5
13
#57
03
#58
b10 5
13
#59
03
#60
12
b0 5
13
#61
03
#62
02
b1 5
13
#63
03
#64
b10 5
13
#65
03
#66
12
b0 5
13
#67
03
#68
02
b1 5
13
#69
03
#70
b10 5
13
#71
03
#72
12
b0 5
13
#73
03
#74
02
b1 5
13
#75
03
#76
b10 5
13
#77
03
#78
12
b0 5
13
#79
03
#80
02
b1 5
13
#81
03
#82
b10 5
13
#83
03
#84
12
b0 5
13
#85
03
#86
02
b1 5
13
#87
03
#88
b10 5
13
#89
03
#90
12
b0 5
13
#91
03
#92
02
b1 5
13
#93
03
#94
b10 5
13
#95
03
#96
12
b0 5
13
#97
03
#98
02
b1 5
13
#99
03
#100
b10 5
13
#101
03
#102
12
b0 5
13
